{"inkVersion":20,"root":[[{"->":"Vivi"},["done",{"#f":5,"#n":"g-0"}],null],"done",{"Vivi":[["^*You approach Vivienne, who instantly gave you a strained look. You decide to carefully ask her about Astira - she mentioned her at the club, after all. You need to change your approach. It is known that the Ventrue like to insult someone you respect...* ",{"#":"speaker: Narrator"},{"#":"portrait: Narrator"},{"#":"layout: Left"},"\n","^Your friends left you? ",{"#":"speaker: Ambrose"},{"#":"portrait: Ambrose"},{"#":"layout: Left"},"\n","^Friends? There’s no friendship in this world. Especially when you want to achieve something. You should know about it, after all. ",{"#":"speaker: Vivienne"},{"#":"portrait: Vivienne"},{"#":"layout: Right"},"\n","^Hm? ",{"#":"speaker: Ambrose"},{"#":"portrait: Ambrose"},{"#":"layout: Left"},"\n","^Astira, Stephen and the entirety of hisposition is just a one big game. You’re his childe, so you should be the one to know something about that. I wonder when Asti’s gonna let it go. ",{"#":"speaker: Vivienne"},{"#":"portrait: Vivienne"},{"#":"layout: Right"},"\n",["ev",{"^->":"Vivi.0.25.$r1"},{"temp=":"$r"},"str",{"->":".^.s"},[{"#n":"$r1"}],"/str","/ev",{"*":".^.^.c-0","flg":18},{"s":["^Let what go? ",{"->":"$r","var":true},null]}],["ev",{"^->":"Vivi.0.26.$r1"},{"temp=":"$r"},"str",{"->":".^.s"},[{"#n":"$r1"}],"/str","/ev",{"*":".^.^.c-1","flg":18},{"s":["^Why do you suggest it's game? ",{"->":"$r","var":true},null]}],["ev",{"^->":"Vivi.0.27.$r1"},{"temp=":"$r"},"str",{"->":".^.s"},[{"#n":"$r1"}],"/str","/ev",{"*":".^.^.c-2","flg":18},{"s":["^*remain silent* ",{"->":"$r","var":true},null]}],{"c-0":["ev",{"^->":"Vivi.0.c-0.$r2"},"/ev",{"temp=":"$r"},{"->":".^.^.25.s"},[{"#n":"$r2"}],{"#":"speaker: Ambrose"},{"#":"portrait: Ambrose"},{"#":"layout: Left"},"\n",{"->":".^.^.g-0"},{"#f":5}],"c-1":["ev",{"^->":"Vivi.0.c-1.$r2"},"/ev",{"temp=":"$r"},{"->":".^.^.26.s"},[{"#n":"$r2"}],{"#":"speaker: Ambrose"},{"#":"portrait: Ambrose"},{"#":"layout: Left"},"\n",{"->":".^.^.g-0"},{"#f":5}],"c-2":["ev",{"^->":"Vivi.0.c-2.$r2"},"/ev",{"temp=":"$r"},{"->":".^.^.27.s"},[{"#n":"$r2"}],{"#":"speaker: Ambrose"},{"#":"portrait: Ambrose"},{"#":"layout: Left"},"\n",{"->":".^.^.g-0"},{"#f":5}],"g-0":["^That whole fuss about manipulating this poor Malkavian... With her abilities, she would have taken the throne in LA or Chicago long ago. She’s always cared about power. ",{"#":"speaker: Vivienne"},{"#":"portrait: Vivienne"},{"#":"layout: Right"},"\n","^And you think that Astira doesn’t care about Stephen? ",{"#":"speaker: Ambrose"},{"#":"portrait: Ambrose"},{"#":"layout: Left"},"\n","^Haha, and you think she cares? Friendship isn’t really her style. ",{"#":"speaker: Vivienne"},{"#":"portrait: Vivienne"},{"#":"layout: Right"},"\n",["ev",{"^->":"Vivi.0.g-0.15.$r1"},{"temp=":"$r"},"str",{"->":".^.s"},[{"#n":"$r1"}],"/str","/ev",{"*":".^.^.c-3","flg":18},{"s":["^You're probably the last person to talk about friendship. ",{"->":"$r","var":true},null]}],["ev",{"^->":"Vivi.0.g-0.16.$r1"},{"temp=":"$r"},"str",{"->":".^.s"},[{"#n":"$r1"}],"/str","/ev",{"*":".^.^.c-4","flg":18},{"s":["^I didn’t know you were such an expert in Kindred’s personalities. ",{"->":"$r","var":true},null]}],{"c-3":["ev",{"^->":"Vivi.0.g-0.c-3.$r2"},"/ev",{"temp=":"$r"},{"->":".^.^.15.s"},[{"#n":"$r2"}],{"#":"speaker: Ambrose"},{"#":"portrait: Ambrose"},{"#":"layout: Left"},"\n","^Maybe I am. But I certainly have a lot to say about the situation on the court. About which you, out of everyone, should know best. ",{"#":"speaker: Vivienne"},{"#":"portrait: Vivienne"},{"#":"layout: Right"},"\n","^Ah, your sire is a part of Primogen, afterall. ",{"#":"speaker: Ambrose"},{"#":"portrait: Ambrose"},{"#":"layout: Left"},"\n","^Finlay doesn’t talk with me about it. Infact, we rarely speak in general lately. He spends most of his time on the Primogen meetings. ",{"#":"speaker: Vivienne"},{"#":"portrait: Vivienne"},{"#":"layout: Right"},"\n","^They plot against the Prince, yeah, I know. ",{"#":"speaker: Ambrose"},{"#":"portrait: Ambrose"},{"#":"layout: Left"},"\n","^What? What are you talking about? ",{"#":"speaker: Vivienne"},{"#":"portrait: Vivienne"},{"#":"layout: Right"},"\n","^I know best about the situation on the court, apparently. ",{"#":"speaker: Ambrose"},{"#":"portrait: Ambrose"},{"#":"layout: Left"},"\n","^Maybe you don’t know anything, since you draw conclusions like that. Nobody tries to overthrow Stephen, if that’s what you imply. ",{"#":"speaker: Vivienne"},{"#":"portrait: Vivienne"},{"#":"layout: Right"},"\n",[["ev",{"^->":"Vivi.0.g-0.c-3.45.0.$r1"},{"temp=":"$r"},"str",{"->":".^.s"},[{"#n":"$r1"}],"/str","/ev",{"*":".^.^.c-0","flg":18},{"s":["^But Astira said... ",{"->":"$r","var":true},null]}],["ev",{"^->":"Vivi.0.g-0.c-3.45.1.$r1"},{"temp=":"$r"},"str",{"->":".^.s"},[{"#n":"$r1"}],"/str","/ev",{"*":".^.^.c-1","flg":18},{"s":["^But Halim said... ",{"->":"$r","var":true},null]}],["ev",{"^->":"Vivi.0.g-0.c-3.45.2.$r1"},{"temp=":"$r"},"str",{"->":".^.s"},[{"#n":"$r1"}],"/str","/ev",{"*":".^.^.c-2","flg":18},{"s":["^*don't say anything* ",{"->":"$r","var":true},null]}],{"c-0":["ev",{"^->":"Vivi.0.g-0.c-3.45.c-0.$r2"},"/ev",{"temp=":"$r"},{"->":".^.^.0.s"},[{"#n":"$r2"}],{"#":"speaker: Ambrose"},{"#":"portrait: Ambrose"},{"#":"layout: Left"},"\n",{"->":"Astira"},{"#f":5}],"c-1":["ev",{"^->":"Vivi.0.g-0.c-3.45.c-1.$r2"},"/ev",{"temp=":"$r"},{"->":".^.^.1.s"},[{"#n":"$r2"}],{"#":"speaker: Ambrose"},{"#":"portrait: Ambrose"},{"#":"layout: Left"},"\n",{"->":"Halim"},{"#f":5}],"c-2":["ev",{"^->":"Vivi.0.g-0.c-3.45.c-2.$r2"},"/ev",{"temp=":"$r"},{"->":".^.^.2.s"},[{"#n":"$r2"}],{"#":"speaker: Ambrose"},{"#":"portrait: Ambrose"},{"#":"layout: Left"},"\n",{"->":"Silent"},{"#f":5}]}],{"#f":5}],"c-4":["ev",{"^->":"Vivi.0.g-0.c-4.$r2"},"/ev",{"temp=":"$r"},{"->":".^.^.16.s"},[{"#n":"$r2"}],{"#":"speaker: Ambrose"},{"#":"portrait: Ambrose"},{"#":"layout: Left"},"\n","^An expert? No, I just can see. I’m deeply shocked that you, after spending so much time with her, still can’t see that. ",{"#":"speaker: Vivienne"},{"#":"portrait: Vivienne"},{"#":"layout: Right"},"\n","^All I can see is scheming Primogen. ",{"#":"speaker: Ambrose"},{"#":"portrait: Ambrose"},{"#":"layout: Left"},"\n","^Scheming? You probably wanted to say “trying to save Stephen from the hands of this lying Lasombra”. ",{"#":"speaker: Vivienne"},{"#":"portrait: Vivienne"},{"#":"layout: Right"},"\n","^Don’t lie, Viv. You’re Finlay’s childe. I know they try to overthrow Stephen. ",{"#":"speaker: Ambrose"},{"#":"portrait: Ambrose"},{"#":"layout: Left"},"\n","^Kid, are you getting worse? Where are you drawing conclusions like these from? ",{"#":"speaker: Vivienne"},{"#":"portrait: Vivienne"},{"#":"layout: Right"},"\n",[["ev",{"^->":"Vivi.0.g-0.c-4.35.0.$r1"},{"temp=":"$r"},"str",{"->":".^.s"},[{"#n":"$r1"}],"/str","/ev",{"*":".^.^.c-0","flg":18},{"s":["^Astira said... ",{"->":"$r","var":true},null]}],["ev",{"^->":"Vivi.0.g-0.c-4.35.1.$r1"},{"temp=":"$r"},"str",{"->":".^.s"},[{"#n":"$r1"}],"/str","/ev",{"*":".^.^.c-1","flg":18},{"s":["^Halim said.. ",{"->":"$r","var":true},null]}],["ev",{"^->":"Vivi.0.g-0.c-4.35.2.$r1"},{"temp=":"$r"},"str",{"->":".^.s"},[{"#n":"$r1"}],"/str","/ev",{"*":".^.^.c-2","flg":18},{"s":["^*don't say anything* ",{"->":"$r","var":true},null]}],{"c-0":["ev",{"^->":"Vivi.0.g-0.c-4.35.c-0.$r2"},"/ev",{"temp=":"$r"},{"->":".^.^.0.s"},[{"#n":"$r2"}],{"#":"speaker: Ambrose"},{"#":"portrait: Ambrose"},{"#":"layout: Left"},"\n",{"->":"Astira"},{"#f":5}],"c-1":["ev",{"^->":"Vivi.0.g-0.c-4.35.c-1.$r2"},"/ev",{"temp=":"$r"},{"->":".^.^.1.s"},[{"#n":"$r2"}],{"#":"speaker: Ambrose"},{"#":"portrait: Ambrose"},{"#":"layout: Left"},"\n",{"->":"Halim"},{"#f":5}],"c-2":["ev",{"^->":"Vivi.0.g-0.c-4.35.c-2.$r2"},"/ev",{"temp=":"$r"},{"->":".^.^.2.s"},[{"#n":"$r2"}],{"#":"speaker: Ambrose"},{"#":"portrait: Ambrose"},{"#":"layout: Left"},"\n",{"->":"Silent"},{"#f":5}]}],{"#f":5}],"#f":5}]}],{"#f":1}],"Astira":["^Astira! Because of her the Primogen breathe down Prince’s neck! Do you still not understand? ",{"#":"speaker: Vivienne"},{"#":"portrait: Vivienne"},{"#":"layout: Right"},"\n","^... ",{"#":"speaker: Ambrose"},{"#":"portrait: Ambrose"},{"#":"layout: Left"},"\n","^Do you even know what their relationship was before Stephen stood at the front of the New Orleans’ Camarilla? ",{"#":"speaker: Vivienne"},{"#":"portrait: Vivienne"},{"#":"layout: Right"},"\n","^No, I don't. ",{"#":"speaker: Ambrose"},{"#":"portrait: Ambrose"},{"#":"layout: Left"},"\n","^Stephen and Astira lived in LA. They worked together and were in close terms with Therese and LaCroix. Astira was... A bit different than she is now. She didn’t have such a strong affinity for power. Maybe it was because she used to be too busy with drinking her sire’s blood... ",{"#":"speaker: Vivienne"},{"#":"portrait: Vivienne"},{"#":"layout: Right"},"\n","^Anyway, she didn’t care about ruling. After Oliver’s death, that she led to, by the way, Stephen did everything he could to bring back this relaxed and party woman. He was doing absolutely everything - and she was taking advantage of it. ",{"#":"speaker: Vivienne"},{"#":"portrait: Vivienne"},{"#":"layout: Right"},"\n","^And when Stephen was chosen to be a Prince here... You know it yourself, that she hasn't left his side ever since. Maybe he thinks that she does this to return the favor after all his help to bounce back after Oliver’s death. ",{"#":"speaker: Vivienne"},{"#":"portrait: Vivienne"},{"#":"layout: Right"},"\n","^Or he doesn’t have any other choice than to trust her... ",{"#":"speaker: Ambrose"},{"#":"portrait: Ambrose"},{"#":"layout: Left"},"\n","^He doesen't? ",{"#":"speaker: Vivienne"},{"#":"portrait: Vivienne"},{"#":"layout: Right"},"\n","^Crone and Kain. ",{"#":"speaker: Ambrose"},{"#":"portrait: Ambrose"},{"#":"layout: Left"},"\n","^Blood bond? ",{"#":"speaker: Vivienne"},{"#":"portrait: Vivienne"},{"#":"layout: Right"},"\n","^Who knows. If she’s such a monster in your eyes... ",{"#":"speaker: Ambrose"},{"#":"portrait: Ambrose"},{"#":"layout: Left"},"\n","^Oh, not at all! I think we would be great friends in other circumstances. Anyway, I’m going back to the party. ",{"#":"speaker: Vivienne"},{"#":"portrait: Vivienne"},{"#":"layout: Right"},"\n","end",{"#f":1}],"Halim":["^Halim? This dirty Tremere? What does he even has to say about that? ",{"#":"speaker: Vivienne"},{"#":"portrait: Vivienne"},{"#":"layout: Right"},"\n","^He’s going out with Stephen, so he probably knows a lot. ",{"#":"speaker: Ambrose"},{"#":"portrait: Ambrose"},{"#":"layout: Left"},"\n","^Haha! That’s a good one. Do you know how many banquets and official parties he accompanied Stephen on? None. ",{"#":"speaker: Vivienne"},{"#":"portrait: Vivienne"},{"#":"layout: Right"},"\n","^... ",{"#":"speaker: Ambrose"},{"#":"portrait: Ambrose"},{"#":"layout: Left"},"\n","^I feel like the Prince spends time with him just because of some sort of humane sentiment. You probably know that they met even before Stephen moved in here? With Astira too. ",{"#":"speaker: Vivienne"},{"#":"portrait: Vivienne"},{"#":"layout: Right"},"\n","^No, I didn’t know that. ",{"#":"speaker: Ambrose"},{"#":"portrait: Ambrose"},{"#":"layout: Left"},"\n","^Stephen and Astira lived in LA. They worked together and were in close terms with Therese and La Croix. Astira was... A bit different than she is now. She didn’t have such a strong affinity for power. Maybe it was because she used to be too busy with drinking her sire’s blood... ",{"#":"speaker: Vivienne"},{"#":"portrait: Vivienne"},{"#":"layout: Right"},"\n","^Anyway, they used to party a lot. And at one of those parties, Stephen met Halim. At first, when Astira’s sire died and Stephen tried to help her get over it, Halim was against it. ",{"#":"speaker: Vivienne"},{"#":"portrait: Vivienne"},{"#":"layout: Right"},"\n","^He tried to pull him away from her. To no avail. Stephen was doing absolutely everything for her - and she was taking advantage of it. He even left LA for her, to Halim’s disappointment. ",{"#":"speaker: Vivienne"},{"#":"portrait: Vivienne"},{"#":"layout: Right"},"\n","^And when Stephen was chosen to be a Prince here... You know it yourself, that she hasn't left his side ever since. And this pathetic Tremere is just jealous. He thinks he’s so important just because he goes to a club with the Prince from time to time. ",{"#":"speaker: Vivienne"},{"#":"portrait: Vivienne"},{"#":"layout: Right"},"\n","^I always thought that Halim and Astira were good. ",{"#":"speaker: Ambrose"},{"#":"portrait: Ambrose"},{"#":"layout: Left"},"\n","^You know what? I feel like Astira would like him only when his head would be a decoration in her living room. ",{"#":"speaker: Vivienne"},{"#":"portrait: Vivienne"},{"#":"layout: Right"},"\n","^Oh? ",{"#":"speaker: Ambrose"},{"#":"portrait: Ambrose"},{"#":"layout: Left"},"\n","^And Halim... He’ll do everything for Stephen to pay all his attention to him instead of Astira. So don’t believe everything he says - you’re the Prince’s childe, everyone will try to win you over. ",{"#":"speaker: Vivienne"},{"#":"portrait: Vivienne"},{"#":"layout: Right"},"\n","^Why? ",{"#":"speaker: Ambrose"},{"#":"portrait: Ambrose"},{"#":"layout: Left"},"\n","^Because you have an impact on him. Everyone knows that Stephen would get himself killed for you. ",{"#":"speaker: Vivienne"},{"#":"portrait: Vivienne"},{"#":"layout: Right"},"\n","^... ",{"#":"speaker: Ambrose"},{"#":"portrait: Ambrose"},{"#":"layout: Left"},"\n","^Anyway, I’m going back to the club. Think about who you want to believe. ",{"#":"speaker: Vivienne"},{"#":"portrait: Vivienne"},{"#":"layout: Right"},"\n","end",{"#f":1}],"Silent":["^Listen, Ambrose. The Primogen don’t want to hurt Stephen. Quite the opposite. Finlay repeatedly said that he’s a good Prince and just needs to stop letting Astira manipulate him like that. ",{"#":"speaker: Vivienne"},{"#":"portrait: Vivienne"},{"#":"layout: Right"},"\n","^You’re not the first person that’s implying this... ",{"#":"speaker: Ambrose"},{"#":"portrait: Ambrose"},{"#":"layout: Left"},"\n","^I’m not? So you see now, I’m not the only one who can see this. I’m deeply shocked that you don’t realize that. You’re his childe, damn it! Stephen would get himself killed for you. ",{"#":"speaker: Vivienne"},{"#":"portrait: Vivienne"},{"#":"layout: Right"},"\n","^You think so? ",{"#":"speaker: Ambrose"},{"#":"portrait: Ambrose"},{"#":"layout: Left"},"\n","^Yeah. Everyone in the court places you two as a prime example of a relationship between a sire and their childe. Astira’s the only problem. ",{"#":"speaker: Vivienne"},{"#":"portrait: Vivienne"},{"#":"layout: Right"},"\n","^I don't know Viv. Stephen trusts her implicitly,so he must have some reasons for it. ",{"#":"speaker: Ambrose"},{"#":"portrait: Ambrose"},{"#":"layout: Left"},"\n","^You know they’ve known each other for along time, right? ",{"#":"speaker: Vivienne"},{"#":"portrait: Vivienne"},{"#":"layout: Right"},"\n","^Yeah. ",{"#":"speaker: Ambrose"},{"#":"portrait: Ambrose"},{"#":"layout: Left"},"\n","^And you know why? ",{"#":"speaker: Vivienne"},{"#":"portrait: Vivienne"},{"#":"layout: Right"},"\n","^They're friends. ",{"#":"speaker: Ambrose"},{"#":"portrait: Ambrose"},{"#":"layout: Left"},"\n","^Well...Stephen and Astira lived in LA. They worked together and were in close terms with Therese and La Croix. Astira was... A bit different than she is now. She didn’t have such a strong affinity for power. Maybe it was because she used to be too busy with drinking her sire’s blood... ",{"#":"speaker: Vivienne"},{"#":"portrait: Vivienne"},{"#":"layout: Right"},"\n","^Anyway, she didn’t care about ruling. After Oliver’s death, that she led to, by the way, Stephen did everything he could to bring back this relaxed and party woman. He was doing absolutely everything - and she was taking advantage of it. ",{"#":"speaker: Vivienne"},{"#":"portrait: Vivienne"},{"#":"layout: Right"},"\n","^And when Stephen was chosen to be a Prince here... You know it yourself, that she hasn't left his side ever since. Maybe he thinks that she does this to return the favor after all his help to bounce back after Oliver’s death. But I wouldn’t say they’re friends. Maybe they used to be. ",{"#":"speaker: Vivienne"},{"#":"portrait: Vivienne"},{"#":"layout: Right"},"\n","^Maybe let’s just drop this...","\n","^You know, you should talk to Stephen. You’re the only person that can bring him to his senses. And don’t trust Astira. ",{"#":"speaker: Vivienne"},{"#":"portrait: Vivienne"},{"#":"layout: Right"},"\n","^Ehh... ",{"#":"speaker: Ambrose"},{"#":"portrait: Ambrose"},{"#":"layout: Left"},"\n","^Do what you want. I’m going back, the party’s waiting. Bye. ",{"#":"speaker: Vivienne"},{"#":"portrait: Vivienne"},{"#":"layout: Right"},"\n","end",{"#f":1}],"#f":1}],"listDefs":{}}